qciconnect_common/__init__.py
qciconnect_common/py.typed
qciconnect_common/qciconnect_conversion/json_conversion.py
qciconnect_common/qciconnect_conversion/__init__.py
qciconnect_common/qciconnect_communication/__init__.py
qciconnect_common/qciconnect_logging/configuration.py
qciconnect_common/qciconnect_logging/__init__.py
qciconnect_common/qciconnect_logging/logger.py
qciconnect_common/qciconnect_settings/__init__.py
qciconnect_common/qciconnect_settings/environment_config.py
qciconnect_common/qciconnect_scheduler/celery_app.py
qciconnect_common/qciconnect_scheduler/__init__.py
qciconnect_common/qciconnect_models/__init__.py
qciconnect_common/qciconnect_models/task_status.py
qciconnect_common/qciconnect_conversion/tests/test_json_numpy_converter.py
qciconnect_common/qciconnect_conversion/tests/test_json_datetime_converter.py
qciconnect_common/qciconnect_communication/grpc/communication_pb2.pyi
qciconnect_common/qciconnect_communication/grpc/communication_pb2.py
qciconnect_common/qciconnect_communication/grpc/communication_pb2_grpc.py
qciconnect_common/qciconnect_communication/grpc/__init__.py
qciconnect_common/qciconnect_communication/grpc/grpc_setting.py
qciconnect_common/qciconnect_models/celery/__init__.py
qciconnect_common/qciconnect_models/celery/result.py
hequate_common/models.py
hequate_common/__init__.py
hequate_common/py.typed
qciconnect/mageia.py
qciconnect/methods.py
qciconnect/result_handling.py
qciconnect/client.py
qciconnect/__init__.py
qciconnect/utils.py
qciconnect/token_managers.py
qciconnect/exceptions.py
qciconnect/qpus.py
qciconnect-0.7.1.dist-info/RECORD
qciconnect-0.7.1.dist-info/WHEEL
qciconnect-0.7.1.dist-info/METADATA
